README.txt
setup.py
src/activiti/__init__.py
src/activiti/api.py
src/activiti/forms.py
src/activiti/multipart.py
src/py_activiti.egg-info/PKG-INFO
src/py_activiti.egg-info/SOURCES.txt
src/py_activiti.egg-info/dependency_links.txt
src/py_activiti.egg-info/entry_points.txt
src/py_activiti.egg-info/requires.txt
src/py_activiti.egg-info/top_level.txt