Metadata-Version: 1.0
Name: py-activiti
Version: 0.1.1a
Summary: Activiti BPMN2.0 API Wrapper
Home-page: https://sourceforge.net/p/pyactiviti/home/Home/
Author: Thierry MICHEL
Author-email: thierry@xtensive.com
License: GPLv3
Keywords: Activiti API BPM 2.0
Platform: UNKNOWN
Classifier: Development Status :: 2 - Pre-Alpha
Classifier: Environment :: Other Environment
Classifier: Intended Audience :: Developers
Classifier: License :: OSI Approved :: GNU Affero General Public License v3
Classifier: Operating System :: OS Independent
Classifier: Programming Language :: Python :: 2.7
Classifier: Topic :: Software Development :: Libraries :: Python Modules
